{
  "db_name": "SQLite",
  "query": "INSERT INTO project_agent_settings (id, project_id, enabled, interval_seconds)\n            VALUES ($1, $2, $3, $4)\n            ON CONFLICT(project_id) DO UPDATE SET\n                enabled = excluded.enabled,\n                interval_seconds = excluded.interval_seconds,\n                updated_at = CURRENT_TIMESTAMP\n            RETURNING\n                id as \"id!: Uuid\",\n                project_id as \"project_id!: Uuid\",\n                enabled as \"enabled!: bool\",\n                interval_seconds as \"interval_seconds!: i32\",\n                created_at as \"created_at!: DateTime<Utc>\",\n                updated_at as \"updated_at!: DateTime<Utc>\"",
  "describe": {
    "columns": [
      {
        "name": "id!: Uuid",
        "ordinal": 0,
        "type_info": "Text"
      },
      {
        "name": "project_id!: Uuid",
        "ordinal": 1,
        "type_info": "Text"
      },
      {
        "name": "enabled!: bool",
        "ordinal": 2,
        "type_info": "Integer"
      },
      {
        "name": "interval_seconds!: i32",
        "ordinal": 3,
        "type_info": "Integer"
      },
      {
        "name": "created_at!: DateTime<Utc>",
        "ordinal": 4,
        "type_info": "Datetime"
      },
      {
        "name": "updated_at!: DateTime<Utc>",
        "ordinal": 5,
        "type_info": "Datetime"
      }
    ],
    "parameters": {
      "Right": 4
    },
    "nullable": [
      false,
      false,
      false,
      false,
      false,
      false
    ]
  },
  "hash": "a525226e1a8166dae246845002532d5cdd1b68e4d25850038bced6d381962389"
}
